CHANGES.rst
MANIFEST.in
setup.py
Products/__init__.py
Products.PloneHotfix20170117.egg-info/PKG-INFO
Products.PloneHotfix20170117.egg-info/SOURCES.txt
Products.PloneHotfix20170117.egg-info/dependency_links.txt
Products.PloneHotfix20170117.egg-info/entry_points.txt
Products.PloneHotfix20170117.egg-info/namespace_packages.txt
Products.PloneHotfix20170117.egg-info/not-zip-safe
Products.PloneHotfix20170117.egg-info/requires.txt
Products.PloneHotfix20170117.egg-info/top_level.txt
Products/PloneHotfix20170117/README.txt
Products/PloneHotfix20170117/__init__.py
Products/PloneHotfix20170117/strformat.py
Products/PloneHotfix20170117/zmi.py
Products/PloneHotfix20170117/www/findResult.dtml
docs/LICENSE.GPL
docs/LICENSE.txt