Metadata-Version: 1.1
Name: Products.PloneHotfix20170117
Version: 1.0
Summary: Various Plone hotfixes, 2017-01-17
Home-page: https://github.com/plone
Author: Plone Security Team
Author-email: security@plone.org
License: GPL
Keywords: plone security hotfix patch
Platform: UNKNOWN
Classifier: Framework :: Plone
Classifier: Programming Language :: Python
